{
    "ביתרנהריה2": {
        "מיקום": "1",
        "קבוצה": "בית\"ר נהריה 2",
        "משחקים": "3",
        "ניצחונות": "3",
        "תיקו": "0",
        "הפסדים": "0",
        "שערים": "18 - 1",
        "הפרש": "+17",
        "נקודות": "9"
    },
    "הפועלעירוניכרמיאל2": {
        "מיקום": "2",
        "קבוצה": "הפועל עירוני כרמיאל 2",
        "משחקים": "3",
        "ניצחונות": "3",
        "תיקו": "0",
        "הפסדים": "0",
        "שערים": "15 - 1",
        "הפרש": "+14",
        "נקודות": "9"
    },
    "הפועליוקנעם": {
        "מיקום": "3",
        "קבוצה": "הפועל יוקנעם",
        "משחקים": "3",
        "ניצחונות": "2",
        "תיקו": "0",
        "הפסדים": "1",
        "שערים": "12 - 10",
        "הפרש": "+2",
        "נקודות": "6"
    },
    "מ.ס.שפרעם": {
        "מיקום": "4",
        "קבוצה": "מ.ס. שפרעם",
        "משחקים": "2",
        "ניצחונות": "1",
        "תיקו": "0",
        "הפסדים": "1",
        "שערים": "10 - 3",
        "הפרש": "+7",
        "נקודות": "3"
    },
    "הפועלחוףהכרמלממ3": {
        "מיקום": "5",
        "קבוצה": "הפועל חוף הכרמל מ\"מ 3",
        "משחקים": "1",
        "ניצחונות": "1",
        "תיקו": "0",
        "הפסדים": "0",
        "שערים": "5 - 0",
        "הפרש": "+5",
        "נקודות": "3"
    },
    "מ.כ.נהלליזראעל": {
        "מיקום": "6",
        "קבוצה": "מ.כ. נהלל יזראעל",
        "משחקים": "2",
        "ניצחונות": "1",
        "תיקו": "0",
        "הפסדים": "1",
        "שערים": "5 - 6",
        "הפרש": "-1",
        "נקודות": "3"
    },
    "הפועלרמותמנשה": {
        "מיקום": "7",
        "קבוצה": "הפועל רמות מנשה",
        "משחקים": "4",
        "ניצחונות": "1",
        "תיקו": "0",
        "הפסדים": "3",
        "שערים": "8 - 13",
        "הפרש": "-5",
        "נקודות": "3"
    },
    "נווהשאנן2": {
        "מיקום": "8",
        "קבוצה": "נווה שאנן 2",
        "משחקים": "0",
        "ניצחונות": "0",
        "תיקו": "0",
        "הפסדים": "0",
        "שערים": "0 - 0",
        "הפרש": "0",
        "נקודות": "0"
    },
    "קריתטבעון": {
        "מיקום": "9",
        "קבוצה": "קרית טבעון",
        "משחקים": "0",
        "ניצחונות": "0",
        "תיקו": "0",
        "הפסדים": "0",
        "שערים": "0 - 0",
        "הפרש": "0",
        "נקודות": "0"
    },
    "הפועלאיחודאעבלין": {
        "מיקום": "10",
        "קבוצה": "הפועל איחוד אעבלין",
        "משחקים": "1",
        "ניצחונות": "0",
        "תיקו": "0",
        "הפסדים": "1",
        "שערים": "0 - 8",
        "הפרש": "-8",
        "נקודות": "0"
    },
    "ביתרנהריה3": {
        "מיקום": "11",
        "קבוצה": "בית\"ר נהריה 3",
        "משחקים": "3",
        "ניצחונות": "0",
        "תיקו": "0",
        "הפסדים": "3",
        "שערים": "2 - 17",
        "הפרש": "-15",
        "נקודות": "0"
    },
    "הפאיחודאעבלין": {
        "מיקום": "12",
        "קבוצה": "הפ' איחוד אעבלין",
        "משחקים": "2",
        "ניצחונות": "0",
        "תיקו": "0",
        "הפסדים": "2",
        "שערים": "0 - 16",
        "הפרש": "-16",
        "נקודות": "0"
    }
}