{
    "מכביקריתגתצופיוס": {
        "href": "/team-details/?season_id=26&team_id=6504",
        "teamId": 6504,
        "מיקום": "1",
        "קבוצה": "מכבי קרית גת \"צו פיוס\"",
        "משחקים": "13",
        "ניצחונות": "11",
        "תיקו": "2",
        "הפסדים": "0",
        "שערים": "14-64",
        "נקודות": "35"
    },
    "מ.ס.בשצופיוס": {
        "href": "/team-details/?season_id=26&team_id=5645",
        "teamId": 5645,
        "מיקום": "2",
        "קבוצה": "מ.ס. ב\"ש \"צו פיוס\"",
        "משחקים": "12",
        "ניצחונות": "9",
        "תיקו": "3",
        "הפסדים": "0",
        "שערים": "5-74",
        "נקודות": "30"
    },
    "הפע.ס.אבוגושמ.ציוןצופיוס": {
        "href": "/team-details/?season_id=26&team_id=5603",
        "teamId": 5603,
        "מיקום": "3",
        "קבוצה": "הפ' ע.ס. אבו גוש מ. ציון \"צו פיוס\"",
        "משחקים": "12",
        "ניצחונות": "8",
        "תיקו": "2",
        "הפסדים": "2",
        "שערים": "18-47",
        "נקודות": "26"
    },
    "ע.ביתשמשצופיוס": {
        "href": "/team-details/?season_id=26&team_id=5114",
        "teamId": 5114,
        "מיקום": "4",
        "קבוצה": "ע.בית שמש \"צו פיוס\"",
        "משחקים": "12",
        "ניצחונות": "8",
        "תיקו": "2",
        "הפסדים": "2",
        "שערים": "15-59",
        "נקודות": "26"
    },
    "מועדוןכדורגלמועצהאזוריתיואב": {
        "href": "/team-details/?season_id=26&team_id=7977",
        "teamId": 7977,
        "מיקום": "5",
        "קבוצה": "מועדון כדורגל מועצה אזורית יואב",
        "משחקים": "13",
        "ניצחונות": "8",
        "תיקו": "1",
        "הפסדים": "4",
        "שערים": "22-43",
        "נקודות": "25"
    },
    "א.ס.אשדודצופיוס": {
        "href": "/team-details/?season_id=26&team_id=7049",
        "teamId": 7049,
        "מיקום": "6",
        "קבוצה": "א.ס. אשדוד \"צו פיוס\"",
        "משחקים": "13",
        "ניצחונות": "7",
        "תיקו": "2",
        "הפסדים": "4",
        "שערים": "24-46",
        "נקודות": "23"
    },
    "מ.כ.מכביע.אשדוד": {
        "href": "/team-details/?season_id=26&team_id=6945",
        "teamId": 6945,
        "מיקום": "7",
        "קבוצה": "מ.כ. מכבי ע. אשדוד",
        "משחקים": "11",
        "ניצחונות": "4",
        "תיקו": "1",
        "הפסדים": "6",
        "שערים": "26-20",
        "נקודות": "13"
    },
    "מ.כ.הפבניאשדודצופיוס": {
        "href": "/team-details/?season_id=26&team_id=4792",
        "teamId": 4792,
        "מיקום": "8",
        "קבוצה": "מ.כ. הפ' בני אשדוד \"צו פיוס\"",
        "משחקים": "12",
        "ניצחונות": "4",
        "תיקו": "0",
        "הפסדים": "8",
        "שערים": "44-15",
        "נקודות": "12"
    },
    "ביתרעירוניקריתגתדודוצופיוס": {
        "href": "/team-details/?season_id=26&team_id=3834",
        "teamId": 3834,
        "מיקום": "9",
        "קבוצה": "בית\"ר עירוני קרית גת דודו \"צו פיוס\"",
        "משחקים": "12",
        "ניצחונות": "3",
        "תיקו": "1",
        "הפסדים": "8",
        "שערים": "39-21",
        "נקודות": "10"
    },
    "הפעירוניגדרהצופיוס": {
        "href": "/team-details/?season_id=26&team_id=3312",
        "teamId": 3312,
        "מיקום": "10",
        "קבוצה": "הפ' עירוני גדרה \"צו פיוס\"",
        "משחקים": "12",
        "ניצחונות": "3",
        "תיקו": "0",
        "הפסדים": "9",
        "שערים": "33-29",
        "נקודות": "9"
    },
    "מועדוןצעירירהט": {
        "href": "/team-details/?season_id=26&team_id=4937",
        "teamId": 4937,
        "מיקום": "11",
        "קבוצה": "מועדון צעירי רהט",
        "משחקים": "12",
        "ניצחונות": "1",
        "תיקו": "0",
        "הפסדים": "11",
        "שערים": "90-13",
        "נקודות": "3"
    },
    "עירוניאשקלוןצופיוס": {
        "href": "/team-details/?season_id=26&team_id=4361",
        "teamId": 4361,
        "מיקום": "12",
        "קבוצה": "עירוני אשקלון \"צו פיוס\"",
        "משחקים": "12",
        "ניצחונות": "0",
        "תיקו": "0",
        "הפסדים": "12",
        "שערים": "115-14",
        "נקודות": "0"
    }
}