{
    "עירוניטבריהעמרי": {
        "href": "/team-details/?season_id=26&team_id=5459",
        "teamId": 5459,
        "מיקום": "1",
        "קבוצה": "עירוני טבריה 'עמרי'",
        "משחקים": "6",
        "ניצחונות": "5",
        "תיקו": "1",
        "הפסדים": "0",
        "שערים": "10-32",
        "נקודות": "16"
    },
    "מ.ס.כפריאסיף": {
        "href": "/team-details/?season_id=26&team_id=4102",
        "teamId": 4102,
        "מיקום": "2",
        "קבוצה": "מ.ס. כפר יאסיף",
        "משחקים": "6",
        "ניצחונות": "5",
        "תיקו": "0",
        "הפסדים": "1",
        "שערים": "6-29",
        "נקודות": "15"
    },
    "מכבינוגידאתאחמד": {
        "href": "/team-details/?season_id=26&team_id=3161",
        "teamId": 3161,
        "מיקום": "3",
        "קבוצה": "מכבי נוג'ידאת אחמד",
        "משחקים": "6",
        "ניצחונות": "5",
        "תיקו": "0",
        "הפסדים": "1",
        "שערים": "13-29",
        "נקודות": "15"
    },
    "הפועלמרוםהגלילצופיוס": {
        "href": "/team-details/?season_id=26&team_id=3164",
        "teamId": 3164,
        "מיקום": "4",
        "קבוצה": "הפועל מרום הגליל \"צו פיוס\"",
        "משחקים": "5",
        "ניצחונות": "4",
        "תיקו": "1",
        "הפסדים": "0",
        "שערים": "7-21",
        "נקודות": "13"
    },
    "צעיריסכנין": {
        "href": "/team-details/?season_id=26&team_id=3066",
        "teamId": 3066,
        "מיקום": "5",
        "קבוצה": "צעירי סכנין",
        "משחקים": "7",
        "ניצחונות": "3",
        "תיקו": "4",
        "הפסדים": "0",
        "שערים": "11-20",
        "נקודות": "13"
    },
    "בנימגאר": {
        "href": "/team-details/?season_id=26&team_id=3268",
        "teamId": 3268,
        "מיקום": "6",
        "קבוצה": "בני מג'אר",
        "משחקים": "7",
        "ניצחונות": "4",
        "תיקו": "1",
        "הפסדים": "2",
        "שערים": "19-10",
        "נקודות": "13"
    },
    "מ.כ.גלילגולןצופיוס": {
        "href": "/team-details/?season_id=26&team_id=3658",
        "teamId": 3658,
        "מיקום": "7",
        "קבוצה": "מ.כ. גליל גולן \"צו פיוס\"",
        "משחקים": "5",
        "ניצחונות": "4",
        "תיקו": "0",
        "הפסדים": "1",
        "שערים": "5-37",
        "נקודות": "12"
    },
    "צעירישעב": {
        "href": "/team-details/?season_id=26&team_id=6907",
        "teamId": 6907,
        "מיקום": "8",
        "קבוצה": "צעירי שעב",
        "משחקים": "6",
        "ניצחונות": "3",
        "תיקו": "2",
        "הפסדים": "1",
        "שערים": "8-23",
        "נקודות": "11"
    },
    "מכביסקציהמעלותתרשיחאצופיוס": {
        "href": "/team-details/?season_id=26&team_id=5400",
        "teamId": 5400,
        "מיקום": "9",
        "קבוצה": "מכבי סקציה מעלות תרשיחא \"צו פיוס\"",
        "משחקים": "7",
        "ניצחונות": "3",
        "תיקו": "1",
        "הפסדים": "3",
        "שערים": "15-25",
        "נקודות": "10"
    },
    "הפועלבניבענה": {
        "href": "/team-details/?season_id=26&team_id=6602",
        "teamId": 6602,
        "מיקום": "10",
        "קבוצה": "הפועל בני בענה",
        "משחקים": "6",
        "ניצחונות": "3",
        "תיקו": "1",
        "הפסדים": "2",
        "שערים": "17-22",
        "נקודות": "10"
    },
    "הפביתשאןמסילותצופיוס": {
        "href": "/team-details/?season_id=26&team_id=5862",
        "teamId": 5862,
        "מיקום": "11",
        "קבוצה": "הפ' בית שאן מסילות \"צו פיוס\"",
        "משחקים": "6",
        "ניצחונות": "3",
        "תיקו": "0",
        "הפסדים": "3",
        "שערים": "27-36",
        "נקודות": "9"
    },
    "הפועלעירוניעראבה": {
        "href": "/team-details/?season_id=26&team_id=3257",
        "teamId": 3257,
        "מיקום": "12",
        "קבוצה": "הפועל עירוני עראבה",
        "משחקים": "6",
        "ניצחונות": "2",
        "תיקו": "2",
        "הפסדים": "2",
        "שערים": "15-18",
        "נקודות": "8"
    },
    "הפועלבועיינה": {
        "href": "/team-details/?season_id=26&team_id=3084",
        "teamId": 3084,
        "מיקום": "13",
        "קבוצה": "הפועל בועיינה",
        "משחקים": "6",
        "ניצחונות": "1",
        "תיקו": "3",
        "הפסדים": "2",
        "שערים": "8-17",
        "נקודות": "6"
    },
    "מכביעירוניטמרה": {
        "href": "/team-details/?season_id=26&team_id=6692",
        "teamId": 6692,
        "מיקום": "14",
        "קבוצה": "מכבי עירוני טמרה",
        "משחקים": "6",
        "ניצחונות": "2",
        "תיקו": "0",
        "הפסדים": "4",
        "שערים": "20-12",
        "נקודות": "6"
    },
    "הפועלדירחנא": {
        "href": "/team-details/?season_id=26&team_id=5442",
        "teamId": 5442,
        "מיקום": "15",
        "קבוצה": "הפועל דיר חנא",
        "משחקים": "6",
        "ניצחונות": "2",
        "תיקו": "0",
        "הפסדים": "4",
        "שערים": "22-10",
        "נקודות": "6"
    },
    "איחודבנימגדלכרום": {
        "href": "/team-details/?season_id=26&team_id=7910",
        "teamId": 7910,
        "מיקום": "16",
        "קבוצה": "איחוד בני מג'דל כרום",
        "משחקים": "5",
        "ניצחונות": "1",
        "תיקו": "1",
        "הפסדים": "3",
        "שערים": "30-14",
        "נקודות": "4"
    },
    "מכביצעיריירכא": {
        "href": "/team-details/?season_id=26&team_id=3933",
        "teamId": 3933,
        "מיקום": "17",
        "קבוצה": "מכבי צעירי ירכא",
        "משחקים": "5",
        "ניצחונות": "1",
        "תיקו": "0",
        "הפסדים": "4",
        "שערים": "18-16",
        "נקודות": "3"
    },
    "הפועליפיע": {
        "href": "/team-details/?season_id=26&team_id=3701",
        "teamId": 3701,
        "מיקום": "18",
        "קבוצה": "הפועל יפיע",
        "משחקים": "6",
        "ניצחונות": "0",
        "תיקו": "1",
        "הפסדים": "5",
        "שערים": "26-8",
        "נקודות": "1"
    },
    "מ.ס.ביתגאן": {
        "href": "/team-details/?season_id=26&team_id=3521",
        "teamId": 3521,
        "מיקום": "19",
        "קבוצה": "מ.ס. בית ג'אן",
        "משחקים": "6",
        "ניצחונות": "0",
        "תיקו": "0",
        "הפסדים": "6",
        "שערים": "54-12",
        "נקודות": "0"
    },
    "הפועלסכנין": {
        "href": "/team-details/?season_id=26&team_id=8180",
        "teamId": 8180,
        "מיקום": "20",
        "קבוצה": "הפועל סכנין",
        "משחקים": "7",
        "ניצחונות": "0",
        "תיקו": "0",
        "הפסדים": "7",
        "שערים": "62-2",
        "נקודות": "0"
    },
    "הפועלטובא": {
        "href": "/team-details/?season_id=26&team_id=3824",
        "teamId": 3824,
        "מיקום": "21",
        "קבוצה": "הפועל טובא",
        "משחקים": "0",
        "ניצחונות": "0",
        "תיקו": "0",
        "הפסדים": "0",
        "שערים": "0-0",
        "נקודות": "0"
    },
    "הפועלמ.א.משגב": {
        "href": "/team-details/?season_id=26&team_id=2091",
        "teamId": 2091,
        "מיקום": "22",
        "קבוצה": "הפועל מ.א. משגב",
        "משחקים": "0",
        "ניצחונות": "0",
        "תיקו": "0",
        "הפסדים": "0",
        "שערים": "0-0",
        "נקודות": "0"
    },
    "מ.ק.גולןקצריןצופיוס": {
        "href": "/team-details/?season_id=26&team_id=5020",
        "teamId": 5020,
        "מיקום": "23",
        "קבוצה": "מ.ק.גולן קצרין \"צו פיוס\"",
        "משחקים": "0",
        "ניצחונות": "0",
        "תיקו": "0",
        "הפסדים": "0",
        "שערים": "0-0",
        "נקודות": "0"
    },
    "עירוניבניכאבול": {
        "href": "/team-details/?season_id=26&team_id=5694",
        "teamId": 5694,
        "מיקום": "24",
        "קבוצה": "עירוני בני כאבול",
        "משחקים": "0",
        "ניצחונות": "0",
        "תיקו": "0",
        "הפסדים": "0",
        "שערים": "0-0",
        "נקודות": "0"
    }
}